cli_scheduler/__init__.py
cli_scheduler/cli_job.py
cli_scheduler/scheduler.py
cli_scheduler/scheduler_handle.py
cli_scheduler/scheduler_job.py
cli_scheduler/constants/__init__.py
cli_scheduler/constants/time_constants.py
cli_scheduler/utils/__init__.py
cli_scheduler/utils/function_utils.py
cli_scheduler/utils/logger_utils.py
cli_scheduler/utils/parse_scheduler_utils.py
cli_scheduler/utils/time_utils.py
python_cli_scheduler-1.1.4.dist-info/LICENSE
python_cli_scheduler-1.1.4.dist-info/METADATA
python_cli_scheduler-1.1.4.dist-info/WHEEL
python_cli_scheduler-1.1.4.dist-info/top_level.txt
python_cli_scheduler-1.1.4.dist-info/RECORD
