Metadata-Version: 2.1
Name: python-cli-scheduler
Version: 1.1.4
Summary: Support scheduling of task via command line interface.
Home-page: https://github.com/hoangthanhlamm/python-cli-scheduler
Author: Lam Hoang
Author-email: hoangthanhlamm@gmail.com
Project-URL: Bug Tracker, https://github.com/hoangthanhlamm/python-cli-scheduler
Classifier: Programming Language :: Python :: 3
Classifier: License :: OSI Approved :: MIT License
Classifier: Operating System :: OS Independent
Requires-Python: >=3.6
License-File: LICENSE
